<?xml version="1.0" encoding="UTF-8"?><record_update table="catalog_ui_policy_action">
    <catalog_ui_policy_action action="INSERT_OR_UPDATE">
        <catalog_item/>
        <catalog_variable>IO:8d0c9aaafb38da10e070fff26eefdc7c</catalog_variable>
        <cleared>false</cleared>
        <disabled>ignore</disabled>
        <field/>
        <mandatory>ignore</mandatory>
        <order>100</order>
        <sys_class_name>catalog_ui_policy_action</sys_class_name>
        <sys_created_by>John.Schwab</sys_created_by>
        <sys_created_on>2024-09-25 13:15:06</sys_created_on>
        <sys_id>279cd22efb38da10e070fff26eefdc81</sys_id>
        <sys_mod_count>0</sys_mod_count>
        <sys_name>request_method</sys_name>
        <sys_package display_value="AX Access Request" source="c53aae751bd1c1508c5143f3cc4bcb89">c53aae751bd1c1508c5143f3cc4bcb89</sys_package>
        <sys_policy/>
        <sys_scope display_value="AX Access Request">c53aae751bd1c1508c5143f3cc4bcb89</sys_scope>
        <sys_update_name>catalog_ui_policy_action_279cd22efb38da10e070fff26eefdc81</sys_update_name>
        <sys_updated_by>John.Schwab</sys_updated_by>
        <sys_updated_on>2024-09-25 13:15:06</sys_updated_on>
        <table/>
        <ui_policy display_value="init">ac9c522efb38da10e070fff26eefdc63</ui_policy>
        <variable>request_method</variable>
        <variable_set display_value="Request Method (integration)">e9ebd2eafb38da10e070fff26eefdc33</variable_set>
        <visible>false</visible>
    </catalog_ui_policy_action>
</record_update>
